tgv/__init__.py
tgv/_tgv copy.py
tgv/api.py
tgv/tgv.py
tgv/utils.py
tgv/deconvolutionshlag/__init__.py
tgv/deconvolutionshlag/deconvolution_schlag.py
tgv/deconvolutionshlag/functionals.py
tgv/denoising/__init__.py
tgv/denoising/main.py
tgv/denoising/objective.py
tgv/descent/__init__.py
tgv/descent/pdhg.py
tgv/descent/pdhg_old.py
tgv/inverse/__init__.py
tgv/inverse/convolve.py
tgv/inverse/extended_tgv.py
tgv/inverse/main.py
tgv/inverse/objective.py
tgv/optical_flow/__init__.py
tgv/optical_flow/main.py
tgv/optical_flow/objective.py
tgv/optical_flow/pyramid.py
tgv/optical_flow/warp.py
tgv-0.0.1.dist-info/LICENSE
tgv-0.0.1.dist-info/METADATA
tgv-0.0.1.dist-info/WHEEL
tgv-0.0.1.dist-info/top_level.txt
tgv-0.0.1.dist-info/RECORD
